{
  "$schema": "https://developer.microsoft.com/json-schemas/fabric/item/report/definition/visualContainer/2.5.0/schema.json",
  "name": "6f9fc7d418b3257f420c",
  "position": {
    "x": 0,
    "y": 0,
    "z": 0,
    "height": 572.30769230769226,
    "width": 1280,
    "tabOrder": 0
  },
  "visual": {
    "visualType": "lineChart",
    "query": {
      "queryState": {
        "Category": {
          "projections": [
            {
              "field": {
                "HierarchyLevel": {
                  "Expression": {
                    "Hierarchy": {
                      "Expression": {
                        "PropertyVariationSource": {
                          "Expression": {
                            "SourceRef": {
                              "Entity": "AMZN"
                            }
                          },
                          "Name": "Variation",
                          "Property": "Date"
                        }
                      },
                      "Hierarchy": "Date Hierarchy"
                    }
                  },
                  "Level": "Year"
                }
              },
              "queryRef": "AMZN.Date.Variation.Date Hierarchy.Year",
              "nativeQueryRef": "Date Year",
              "active": true
            },
            {
              "field": {
                "HierarchyLevel": {
                  "Expression": {
                    "Hierarchy": {
                      "Expression": {
                        "PropertyVariationSource": {
                          "Expression": {
                            "SourceRef": {
                              "Entity": "AMZN"
                            }
                          },
                          "Name": "Variation",
                          "Property": "Date"
                        }
                      },
                      "Hierarchy": "Date Hierarchy"
                    }
                  },
                  "Level": "Quarter"
                }
              },
              "queryRef": "AMZN.Date.Variation.Date Hierarchy.Quarter",
              "nativeQueryRef": "Date Quarter",
              "active": true
            },
            {
              "field": {
                "HierarchyLevel": {
                  "Expression": {
                    "Hierarchy": {
                      "Expression": {
                        "PropertyVariationSource": {
                          "Expression": {
                            "SourceRef": {
                              "Entity": "AMZN"
                            }
                          },
                          "Name": "Variation",
                          "Property": "Date"
                        }
                      },
                      "Hierarchy": "Date Hierarchy"
                    }
                  },
                  "Level": "Month"
                }
              },
              "queryRef": "AMZN.Date.Variation.Date Hierarchy.Month",
              "nativeQueryRef": "Date Month",
              "active": true
            },
            {
              "field": {
                "HierarchyLevel": {
                  "Expression": {
                    "Hierarchy": {
                      "Expression": {
                        "PropertyVariationSource": {
                          "Expression": {
                            "SourceRef": {
                              "Entity": "AMZN"
                            }
                          },
                          "Name": "Variation",
                          "Property": "Date"
                        }
                      },
                      "Hierarchy": "Date Hierarchy"
                    }
                  },
                  "Level": "Day"
                }
              },
              "queryRef": "AMZN.Date.Variation.Date Hierarchy.Day",
              "nativeQueryRef": "Date Day",
              "active": true
            }
          ]
        },
        "Y": {
          "projections": [
            {
              "field": {
                "Aggregation": {
                  "Expression": {
                    "Column": {
                      "Expression": {
                        "SourceRef": {
                          "Entity": "AMZN"
                        }
                      },
                      "Property": "High"
                    }
                  },
                  "Function": 0
                }
              },
              "queryRef": "Sum(AMZN.High)",
              "nativeQueryRef": "Sum of High"
            },
            {
              "field": {
                "Aggregation": {
                  "Expression": {
                    "Column": {
                      "Expression": {
                        "SourceRef": {
                          "Entity": "AMZN"
                        }
                      },
                      "Property": "Low"
                    }
                  },
                  "Function": 0
                }
              },
              "queryRef": "Sum(AMZN.Low)",
              "nativeQueryRef": "Sum of Low"
            }
          ]
        }
      }
    },
    "drillFilterOtherVisuals": true
  },
  "filterConfig": {
    "filters": [
      {
        "name": "3a38d170d2907c4caa40",
        "field": {
          "Aggregation": {
            "Expression": {
              "Column": {
                "Expression": {
                  "SourceRef": {
                    "Entity": "AMZN"
                  }
                },
                "Property": "High"
              }
            },
            "Function": 0
          }
        },
        "type": "Advanced"
      },
      {
        "name": "5913208848326c98ae84",
        "field": {
          "HierarchyLevel": {
            "Expression": {
              "Hierarchy": {
                "Expression": {
                  "PropertyVariationSource": {
                    "Expression": {
                      "SourceRef": {
                        "Entity": "AMZN"
                      }
                    },
                    "Name": "Variation",
                    "Property": "Date"
                  }
                },
                "Hierarchy": "Date Hierarchy"
              }
            },
            "Level": "Year"
          }
        },
        "type": "Advanced"
      },
      {
        "name": "c22d8ccff2279e1d6209",
        "field": {
          "HierarchyLevel": {
            "Expression": {
              "Hierarchy": {
                "Expression": {
                  "PropertyVariationSource": {
                    "Expression": {
                      "SourceRef": {
                        "Entity": "AMZN"
                      }
                    },
                    "Name": "Variation",
                    "Property": "Date"
                  }
                },
                "Hierarchy": "Date Hierarchy"
              }
            },
            "Level": "Quarter"
          }
        },
        "type": "Categorical"
      },
      {
        "name": "94705b76acfb82c403ea",
        "field": {
          "HierarchyLevel": {
            "Expression": {
              "Hierarchy": {
                "Expression": {
                  "PropertyVariationSource": {
                    "Expression": {
                      "SourceRef": {
                        "Entity": "AMZN"
                      }
                    },
                    "Name": "Variation",
                    "Property": "Date"
                  }
                },
                "Hierarchy": "Date Hierarchy"
              }
            },
            "Level": "Month"
          }
        },
        "type": "Categorical"
      },
      {
        "name": "a7f1f575a6a01f6fbddd",
        "field": {
          "HierarchyLevel": {
            "Expression": {
              "Hierarchy": {
                "Expression": {
                  "PropertyVariationSource": {
                    "Expression": {
                      "SourceRef": {
                        "Entity": "AMZN"
                      }
                    },
                    "Name": "Variation",
                    "Property": "Date"
                  }
                },
                "Hierarchy": "Date Hierarchy"
              }
            },
            "Level": "Day"
          }
        },
        "type": "Advanced"
      },
      {
        "name": "1f25ecd1b436ac710652",
        "field": {
          "Aggregation": {
            "Expression": {
              "Column": {
                "Expression": {
                  "SourceRef": {
                    "Entity": "AMZN"
                  }
                },
                "Property": "Low"
              }
            },
            "Function": 0
          }
        },
        "type": "Advanced"
      }
    ]
  }
}